selenium_cmd/__init__.py
selenium_cmd/argument_parser.py
selenium_cmd/decorators.py
selenium_cmd/selenium_cmd.py
selenium_cmd-0.0.2.dist-info/LICENSE
selenium_cmd-0.0.2.dist-info/METADATA
selenium_cmd-0.0.2.dist-info/WHEEL
selenium_cmd-0.0.2.dist-info/top_level.txt
selenium_cmd-0.0.2.dist-info/RECORD
