Metadata-Version: 2.1
Name: selenium-cmd
Version: 0.0.2
Summary: Tool to control Selenium from command line
Home-page: UNKNOWN
Author: Patrick Klein
License: MIT
Project-URL: Source, https://github.com/patkle/selenium-cmd
Keywords: selenium xpath testing
Platform: UNKNOWN
Classifier: Intended Audience :: Developers
Classifier: License :: OSI Approved :: MIT License
Classifier: Programming Language :: Python :: 3
Classifier: Topic :: Utilities
Requires-Python: >=3
Requires-Dist: selenium
Requires-Dist: parsel
Requires-Dist: importlib-metadata (~=1.0) ; python_version < "3.8"
